.gitignore
README.md
release.sh
setup.py
pyconfyg/__init__.py
pyconfyg/ast.py
pyconfyg/core.py
pyconfyg/exceptions.py
pyconfyg.egg-info/PKG-INFO
pyconfyg.egg-info/SOURCES.txt
pyconfyg.egg-info/dependency_links.txt
pyconfyg.egg-info/requires.txt
pyconfyg.egg-info/top_level.txt
tests/test_pyconfyg.py